qiscusapi/__init__.py
qiscusapi/sdk.py
qiscusapi-0.0.1.dist-info/DESCRIPTION.rst
qiscusapi-0.0.1.dist-info/METADATA
qiscusapi-0.0.1.dist-info/RECORD
qiscusapi-0.0.1.dist-info/WHEEL
qiscusapi-0.0.1.dist-info/metadata.json
qiscusapi-0.0.1.dist-info/top_level.txt
