Metadata-Version: 2.0
Name: qiscusapi
Version: 0.0.1
Summary: Python wrapper for Qiscus SDK RESTful API
Home-page: https://bitbucket.org/nurcholisart/qiscus-sdk-python
Author: nurcholis art
Author-email: nurcholisart@gmail.com
License: MIT
Platform: UNKNOWN
Classifier: Development Status :: 3 - Alpha
Classifier: Intended Audience :: Developers
Classifier: License :: OSI Approved :: MIT License
Classifier: Programming Language :: Python :: 2.7
Classifier: Programming Language :: Python :: 3.5
Classifier: Topic :: Software Development :: Libraries :: Python Modules
Requires-Dist: requests
